gsitk/__init__.py
gsitk/config.py
gsitk/pipe.py
gsitk/utils.py
gsitk/classifiers/__init__.py
gsitk/classifiers/vader.py
gsitk/datasets/datasets.py
gsitk/datasets/imdb.py
gsitk/datasets/imdb.yml
gsitk/datasets/imdb_unsup.py
gsitk/datasets/imdb_unsup.yml
gsitk/datasets/multidomain.py
gsitk/datasets/multidomain.yml
gsitk/datasets/pl04.py
gsitk/datasets/pl04.yaml
gsitk/datasets/pl05.py
gsitk/datasets/pl05.yaml
gsitk/datasets/semeval07.py
gsitk/datasets/semeval07.yml
gsitk/datasets/semeval13.py
gsitk/datasets/semeval13.yaml
gsitk/datasets/semeval14.py
gsitk/datasets/semeval14.yaml
gsitk/datasets/sentiment140.py
gsitk/datasets/sentiment140.yml
gsitk/datasets/sst.py
gsitk/datasets/sst.yml
gsitk/datasets/sts.py
gsitk/datasets/sts.yml
gsitk/datasets/utils.py
gsitk/datasets/vader.py
gsitk/datasets/vader.yml
gsitk/evaluation/evaluation.py
gsitk/features/doc2vec.py
gsitk/features/embeddings.py
gsitk/features/features.py
gsitk/features/simon.py
gsitk/features/sswe.py
gsitk/features/sswe.yml
gsitk/features/utils.py
gsitk/features/wn_similarity.py
gsitk/features/word2vec.py
gsitk/preprocess/__init__.py
gsitk/preprocess/embeddings_trick.py
gsitk/preprocess/normalize.py
gsitk/preprocess/pprocess_twitter.py
gsitk/preprocess/simple.py
gsitk/preprocess/stopwords.py
gsitk/resources/semeval07.tar.gz
gsitk-0.2.5.dist-info/LICENSE.txt
gsitk-0.2.5.dist-info/METADATA
gsitk-0.2.5.dist-info/NOTICE
gsitk-0.2.5.dist-info/WHEEL
gsitk-0.2.5.dist-info/top_level.txt
gsitk-0.2.5.dist-info/RECORD
